pichromecast.py
pichromecast-0.5.dist-info/LICENSE
pichromecast-0.5.dist-info/METADATA
pichromecast-0.5.dist-info/WHEEL
pichromecast-0.5.dist-info/top_level.txt
pichromecast-0.5.dist-info/RECORD
