Metadata-Version: 2.1
Name: pichromecast
Version: 0.5
Summary: Library for MicroPython to communicate with the Google Chromecast.
Home-page: https://github.com/GitHub30/pichromecast
Author: Tomofumi Inoue
Author-email: funaox@gmail.com
License: MIT
Project-URL: Bug Tracker, https://github.com/GitHub30/pichromecast/issues
Classifier: Programming Language :: Python :: 3
Classifier: License :: OSI Approved :: MIT License
Classifier: Intended Audience :: Developers
Classifier: Programming Language :: Python :: Implementation :: MicroPython
Classifier: Programming Language :: Python
Classifier: Programming Language :: Python :: 3
Classifier: Programming Language :: Python :: 3.6
Classifier: Programming Language :: Python :: 3.7
Classifier: Programming Language :: Python :: 3.8
Classifier: Programming Language :: Python :: 3.9
Classifier: Programming Language :: Python :: 3.10
Classifier: Programming Language :: Python :: 3.11
Classifier: Programming Language :: Python :: 3.12
Classifier: Programming Language :: Python :: 3 :: Only
Classifier: Topic :: Utilities
Classifier: Topic :: Software Development :: Libraries :: Python Modules
Classifier: Topic :: System :: Networking
License-File: LICENSE
